random_name_generator_rendev/__init__.py
random_name_generator_rendev/generator.py
random_name_generator_rendev-1.0.0.1.dist-info/METADATA
random_name_generator_rendev-1.0.0.1.dist-info/WHEEL
random_name_generator_rendev-1.0.0.1.dist-info/top_level.txt
random_name_generator_rendev-1.0.0.1.dist-info/RECORD
