Metadata-Version: 2.4
Name: random_name_generator_rendev
Version: 1.0.0.1
Summary: A Python library for generating random names using vowels and consonants.
Author: Ronchetti Ezequiel Nicolás
Author-email: RonchettiEzequielNicolas@hotmail.com
Classifier: Programming Language :: Python :: 3
Classifier: License :: OSI Approved :: MIT License
Classifier: Operating System :: OS Independent
Requires-Python: >=3.6
Dynamic: author
Dynamic: author-email
Dynamic: classifier
Dynamic: description
Dynamic: description-content-type
Dynamic: requires-python
Dynamic: summary
